{
    "id": 2256,
    "deadlineCodeId": 3,
    "billNumber": 302,
    "sessionLawChapterNumber": null,
    "sponsorId": 200,
    "carrierId": null,
    "drafterStaffMemberId": 24,
    "billType": {
        "id": 1,
        "description": "House Bill",
        "code": "HB",
        "sortOrder": 6,
        "chamber": "HOUSE"
    },
    "draft": {
        "id": 2256,
        "draftNumber": "LC2256",
        "date": "2025-01-24T13:20:14",
        "shortTitle": "Revising punitive damages laws and procedures",
        "description": null,
        "requesterId": 200,
        "requesterType": "LEGISLATOR",
        "billStatuses": [
            {
                "id": 6618,
                "timeStamp": "2024-12-07T15:09:59.681318",
                "standingCommitteeId": null,
                "billStatusCode": {
                    "id": 5,
                    "code": "1",
                    "name": "(LC) Drafter Assigned",
                    "actionWeight": "HARD",
                    "chamber": "HOUSE",
                    "billProgressCategory": {
                        "id": 2,
                        "code": "10",
                        "description": "In Drafting Process"
                    },
                    "standingCommitteeStatusGrouping": {
                        "id": 1,
                        "name": "test_name"
                    }
                }
            },
            {
                "id": 15703,
                "timeStamp": "2025-01-09T11:11:39.884667",
                "standingCommitteeId": null,
                "billStatusCode": {
                    "id": 14,
                    "code": "12",
                    "name": "(LC) Draft in Legal Review",
                    "actionWeight": "HARD",
                    "chamber": "HOUSE",
                    "billProgressCategory": {
                        "id": 2,
                        "code": "10",
                        "description": "In Drafting Process"
                    },
                    "standingCommitteeStatusGrouping": {
                        "id": 1,
                        "name": "test_name"
                    }
                }
            },
            {
                "id": 15979,
                "timeStamp": "2025-01-10T08:50:50.987496",
                "standingCommitteeId": null,
                "billStatusCode": {
                    "id": 15,
                    "code": "13",
                    "name": "(LC) Draft in Edit",
                    "actionWeight": "HARD",
                    "chamber": "HOUSE",
                    "billProgressCategory": {
                        "id": 2,
                        "code": "10",
                        "description": "In Drafting Process"
                    },
                    "standingCommitteeStatusGrouping": {
                        "id": 1,
                        "name": "test_name"
                    }
                }
            },
            {
                "id": 16512,
                "timeStamp": "2025-01-10T16:28:07.201538",
                "standingCommitteeId": null,
                "billStatusCode": {
                    "id": 19,
                    "code": "17",
                    "name": "(LC) Draft in Input/Proofing",
                    "actionWeight": "HARD",
                    "chamber": "HOUSE",
                    "billProgressCategory": {
                        "id": 2,
                        "code": "10",
                        "description": "In Drafting Process"
                    },
                    "standingCommitteeStatusGrouping": {
                        "id": 1,
                        "name": "test_name"
                    }
                }
            },
            {
                "id": 16569,
                "timeStamp": "2025-01-11T08:46:27.26819",
                "standingCommitteeId": null,
                "billStatusCode": {
                    "id": 20,
                    "code": "18",
                    "name": "(LC) Draft in Final Drafter Review",
                    "actionWeight": "HARD",
                    "chamber": "HOUSE",
                    "billProgressCategory": {
                        "id": 2,
                        "code": "10",
                        "description": "In Drafting Process"
                    },
                    "standingCommitteeStatusGrouping": {
                        "id": 1,
                        "name": "test_name"
                    }
                }
            },
            {
                "id": 16586,
                "timeStamp": "2025-01-11T09:49:18.101221",
                "standingCommitteeId": null,
                "billStatusCode": {
                    "id": 26,
                    "code": "24",
                    "name": "(LC) Draft in Assembly",
                    "actionWeight": "HARD",
                    "chamber": "HOUSE",
                    "billProgressCategory": {
                        "id": 2,
                        "code": "10",
                        "description": "In Drafting Process"
                    },
                    "standingCommitteeStatusGrouping": {
                        "id": 1,
                        "name": "test_name"
                    }
                }
            },
            {
                "id": 17176,
                "timeStamp": "2025-01-14T07:52:28.744644",
                "standingCommitteeId": null,
                "billStatusCode": {
                    "id": 24,
                    "code": "22",
                    "name": "(LC) Draft Ready for Delivery",
                    "actionWeight": "HARD",
                    "chamber": "HOUSE",
                    "billProgressCategory": {
                        "id": 2,
                        "code": "10",
                        "description": "In Drafting Process"
                    },
                    "standingCommitteeStatusGrouping": {
                        "id": 1,
                        "name": "test_name"
                    }
                }
            },
            {
                "id": 24792,
                "timeStamp": "2025-01-22T16:03:55.327465",
                "standingCommitteeId": null,
                "billStatusCode": {
                    "id": 25,
                    "code": "23",
                    "name": "(LC) Draft Delivered to Requester",
                    "actionWeight": "HARD",
                    "chamber": "HOUSE",
                    "billProgressCategory": {
                        "id": 2,
                        "code": "10",
                        "description": "In Drafting Process"
                    },
                    "standingCommitteeStatusGrouping": {
                        "id": 1,
                        "name": "test_name"
                    }
                }
            },
            {
                "id": 25682,
                "timeStamp": "2025-01-23T15:39:59.048277",
                "standingCommitteeId": null,
                "billStatusCode": {
                    "id": 284,
                    "code": "500",
                    "name": "(H) Introduced",
                    "actionWeight": "HARD",
                    "chamber": "HOUSE",
                    "billProgressCategory": {
                        "id": 3,
                        "code": "20",
                        "description": "In First House--Introduced"
                    },
                    "standingCommitteeStatusGrouping": {
                        "id": 1,
                        "name": "test_name"
                    }
                }
            },
            {
                "id": 25692,
                "timeStamp": "2025-01-23T15:42:03",
                "standingCommitteeId": null,
                "billStatusCode": {
                    "id": 289,
                    "code": "505",
                    "name": "(H) Fiscal Note Requested",
                    "actionWeight": "SOFT",
                    "chamber": "HOUSE",
                    "billProgressCategory": {
                        "id": 1,
                        "code": "0",
                        "description": "Probably Dead"
                    },
                    "standingCommitteeStatusGrouping": {
                        "id": 1,
                        "name": "test_name"
                    }
                }
            },
            {
                "id": 26006,
                "timeStamp": "2025-01-24T11:26:13.80372",
                "standingCommitteeId": 11,
                "billStatusCode": {
                    "id": 286,
                    "code": "502",
                    "name": "(H) Referred to Committee",
                    "actionWeight": "HARD",
                    "chamber": "HOUSE",
                    "billProgressCategory": {
                        "id": 5,
                        "code": "30",
                        "description": "In First House Committee--Nontabled"
                    },
                    "standingCommitteeStatusGrouping": {
                        "id": 1,
                        "name": "test_name"
                    }
                }
            },
            {
                "id": 26100,
                "timeStamp": "2025-01-24T13:08:53.156086",
                "standingCommitteeId": null,
                "billStatusCode": {
                    "id": 285,
                    "code": "501",
                    "name": "(H) First Reading",
                    "actionWeight": "SOFT",
                    "chamber": "HOUSE",
                    "billProgressCategory": {
                        "id": 3,
                        "code": "20",
                        "description": "In First House--Introduced"
                    },
                    "standingCommitteeStatusGrouping": {
                        "id": 1,
                        "name": "test_name"
                    }
                }
            },
            {
                "id": 27961,
                "timeStamp": "2025-01-28T14:08:53.96394",
                "standingCommitteeId": 11,
                "billStatusCode": {
                    "id": 295,
                    "code": "512",
                    "name": "(H) Hearing",
                    "actionWeight": "HARD",
                    "chamber": "HOUSE",
                    "billProgressCategory": {
                        "id": 5,
                        "code": "30",
                        "description": "In First House Committee--Nontabled"
                    },
                    "standingCommitteeStatusGrouping": {
                        "id": 1,
                        "name": "test_name"
                    }
                }
            },
            {
                "id": 29093,
                "timeStamp": "2025-01-30T07:07:19",
                "standingCommitteeId": null,
                "billStatusCode": {
                    "id": 290,
                    "code": "506",
                    "name": "(H) Fiscal Note Received",
                    "actionWeight": "SOFT",
                    "chamber": "HOUSE",
                    "billProgressCategory": {
                        "id": 1,
                        "code": "0",
                        "description": "Probably Dead"
                    },
                    "standingCommitteeStatusGrouping": {
                        "id": 1,
                        "name": "test_name"
                    }
                }
            },
            {
                "id": 30941,
                "timeStamp": "2025-02-03T13:54:40.739714",
                "standingCommitteeId": null,
                "billStatusCode": {
                    "id": 282,
                    "code": "448",
                    "name": "(H) Fiscal Note Unsigned",
                    "actionWeight": "SOFT",
                    "chamber": "HOUSE",
                    "billProgressCategory": {
                        "id": 1,
                        "code": "0",
                        "description": "Probably Dead"
                    },
                    "standingCommitteeStatusGrouping": {
                        "id": 1,
                        "name": "test_name"
                    }
                }
            },
            {
                "id": 31153,
                "timeStamp": "2025-02-03T16:11:11",
                "standingCommitteeId": null,
                "billStatusCode": {
                    "id": 291,
                    "code": "507",
                    "name": "(H) Fiscal Note Printed",
                    "actionWeight": "SOFT",
                    "chamber": "HOUSE",
                    "billProgressCategory": {
                        "id": 1,
                        "code": "0",
                        "description": "Probably Dead"
                    },
                    "standingCommitteeStatusGrouping": {
                        "id": 1,
                        "name": "test_name"
                    }
                }
            },
            {
                "id": 32731,
                "timeStamp": "2025-02-06T12:07:30.966006",
                "standingCommitteeId": 11,
                "billStatusCode": {
                    "id": 299,
                    "code": "516",
                    "name": "(H) Committee Executive Action--Bill Passed",
                    "actionWeight": "HARD",
                    "chamber": "HOUSE",
                    "billProgressCategory": {
                        "id": 5,
                        "code": "30",
                        "description": "In First House Committee--Nontabled"
                    },
                    "standingCommitteeStatusGrouping": {
                        "id": 1,
                        "name": "test_name"
                    }
                }
            },
            {
                "id": 32852,
                "timeStamp": "2025-02-06T13:33:43",
                "standingCommitteeId": 11,
                "billStatusCode": {
                    "id": 313,
                    "code": "530",
                    "name": "(H) Committee Report--Bill Passed",
                    "actionWeight": "HARD",
                    "chamber": "HOUSE",
                    "billProgressCategory": {
                        "id": 6,
                        "code": "40",
                        "description": "In First House--Out of Committee"
                    },
                    "standingCommitteeStatusGrouping": {
                        "id": 1,
                        "name": "test_name"
                    }
                }
            },
            {
                "id": 34985,
                "timeStamp": "2025-02-12T13:00:00",
                "standingCommitteeId": null,
                "billStatusCode": {
                    "id": 335,
                    "code": "553",
                    "name": "(H) Scheduled for 2nd Reading",
                    "actionWeight": "SOFT",
                    "chamber": "HOUSE",
                    "billProgressCategory": {
                        "id": 1,
                        "code": "0",
                        "description": "Probably Dead"
                    },
                    "standingCommitteeStatusGrouping": {
                        "id": 1,
                        "name": "test_name"
                    }
                }
            },
            {
                "id": 35557,
                "timeStamp": "2025-02-12T13:59:00",
                "standingCommitteeId": null,
                "billStatusCode": {
                    "id": 337,
                    "code": "556",
                    "name": "(H) 2nd Reading Passed",
                    "actionWeight": "HARD",
                    "chamber": "HOUSE",
                    "billProgressCategory": {
                        "id": 7,
                        "code": "50",
                        "description": "In First House--Through 2nd Reading"
                    },
                    "standingCommitteeStatusGrouping": {
                        "id": 1,
                        "name": "test_name"
                    }
                }
            },
            {
                "id": 35674,
                "timeStamp": "2025-02-13T13:00:00",
                "standingCommitteeId": null,
                "billStatusCode": {
                    "id": 374,
                    "code": "594",
                    "name": "(H) Scheduled for 3rd Reading",
                    "actionWeight": "SOFT",
                    "chamber": "HOUSE",
                    "billProgressCategory": {
                        "id": 1,
                        "code": "0",
                        "description": "Probably Dead"
                    },
                    "standingCommitteeStatusGrouping": {
                        "id": 1,
                        "name": "test_name"
                    }
                }
            },
            {
                "id": 36417,
                "timeStamp": "2025-02-13T14:22:00",
                "standingCommitteeId": null,
                "billStatusCode": {
                    "id": 376,
                    "code": "596",
                    "name": "(H) 3rd Reading Passed",
                    "actionWeight": "HARD",
                    "chamber": "HOUSE",
                    "billProgressCategory": {
                        "id": 8,
                        "code": "60",
                        "description": "In First House--Through 3rd Reading"
                    },
                    "standingCommitteeStatusGrouping": {
                        "id": 1,
                        "name": "test_name"
                    }
                }
            },
            {
                "id": 36915,
                "timeStamp": "2025-02-14T11:45:44.169906",
                "standingCommitteeId": null,
                "billStatusCode": {
                    "id": 384,
                    "code": "605",
                    "name": "(H) Transmitted to Senate",
                    "actionWeight": "HARD",
                    "chamber": "HOUSE",
                    "billProgressCategory": {
                        "id": 9,
                        "code": "70",
                        "description": "Transmitted to Second House"
                    },
                    "standingCommitteeStatusGrouping": {
                        "id": 1,
                        "name": "test_name"
                    }
                }
            },
            {
                "id": 36924,
                "timeStamp": "2025-02-14T11:50:55.771447",
                "standingCommitteeId": 31,
                "billStatusCode": {
                    "id": 55,
                    "code": "103",
                    "name": "(S) Referred to Committee",
                    "actionWeight": "HARD",
                    "chamber": "SENATE",
                    "billProgressCategory": {
                        "id": 11,
                        "code": "80",
                        "description": "In Second House Committee--Nontabled"
                    },
                    "standingCommitteeStatusGrouping": {
                        "id": 1,
                        "name": "test_name"
                    }
                }
            },
            {
                "id": 55617,
                "timeStamp": "2025-03-14T09:07:29.925663",
                "standingCommitteeId": 31,
                "billStatusCode": {
                    "id": 65,
                    "code": "113",
                    "name": "(S) Hearing",
                    "actionWeight": "HARD",
                    "chamber": "SENATE",
                    "billProgressCategory": {
                        "id": 11,
                        "code": "80",
                        "description": "In Second House Committee--Nontabled"
                    },
                    "standingCommitteeStatusGrouping": {
                        "id": 1,
                        "name": "test_name"
                    }
                }
            },
            {
                "id": 63255,
                "timeStamp": "2025-03-28T07:15:28",
                "standingCommitteeId": 31,
                "billStatusCode": {
                    "id": 76,
                    "code": "124",
                    "name": "(S) Tabled in Committee",
                    "actionWeight": "HARD",
                    "chamber": "SENATE",
                    "billProgressCategory": {
                        "id": 4,
                        "code": "25",
                        "description": "In First House Committee--Tabled"
                    },
                    "standingCommitteeStatusGrouping": {
                        "id": 1,
                        "name": "test_name"
                    }
                }
            }
        ],
        "legalNote": false,
        "sessionId": 2,
        "fiscalNote": true,
        "fiscalAnalystId": null,
        "preIntroRequired": false,
        "subjects": [
            {
                "id": 35818,
                "subjectCode": {
                    "id": 116,
                    "code": "REM",
                    "description": "Remedies  (see also: Liability; Torts)",
                    "revenueAndAprops": null,
                    "voteMajorityType": "SIMPLE",
                    "primary": true
                }
            },
            {
                "id": 83855,
                "subjectCode": {
                    "id": 88,
                    "code": "LIA",
                    "description": "Liability  (see also: Remedies; Torts)",
                    "revenueAndAprops": null,
                    "voteMajorityType": "SIMPLE",
                    "primary": true
                }
            },
            {
                "id": 83856,
                "subjectCode": {
                    "id": 145,
                    "code": "TORT",
                    "description": "Torts  (see also: Remedies;  Liabilities)",
                    "revenueAndAprops": null,
                    "voteMajorityType": "SIMPLE",
                    "primary": true
                }
            }
        ],
        "byRequestOfs": []
    },
    "enrolled": null,
    "versionNumber": 1,
    "sessionId": 2
}