{
    "id": 2770,
    "deadlineCodeId": 3,
    "billNumber": 811,
    "sessionLawChapterNumber": null,
    "sponsorId": 178,
    "carrierId": null,
    "drafterStaffMemberId": 25,
    "billType": {
        "id": 1,
        "description": "House Bill",
        "code": "HB",
        "sortOrder": 6,
        "chamber": "HOUSE"
    },
    "draft": {
        "id": 2770,
        "draftNumber": "LC2787",
        "date": "2025-02-27T14:02:45",
        "shortTitle": "Increase the generating capacity for customer-generated electricity",
        "description": null,
        "requesterId": 178,
        "requesterType": "LEGISLATOR",
        "billStatuses": [
            {
                "id": 7798,
                "timeStamp": "2024-12-11T08:08:18.707546",
                "standingCommitteeId": null,
                "billStatusCode": {
                    "id": 5,
                    "code": "1",
                    "name": "(LC) Drafter Assigned",
                    "actionWeight": "HARD",
                    "chamber": "HOUSE",
                    "billProgressCategory": {
                        "id": 2,
                        "code": "10",
                        "description": "In Drafting Process"
                    },
                    "standingCommitteeStatusGrouping": {
                        "id": 1,
                        "name": "test_name"
                    }
                }
            },
            {
                "id": 40527,
                "timeStamp": "2025-02-19T17:17:58.361841",
                "standingCommitteeId": null,
                "billStatusCode": {
                    "id": 14,
                    "code": "12",
                    "name": "(LC) Draft in Legal Review",
                    "actionWeight": "HARD",
                    "chamber": "HOUSE",
                    "billProgressCategory": {
                        "id": 2,
                        "code": "10",
                        "description": "In Drafting Process"
                    },
                    "standingCommitteeStatusGrouping": {
                        "id": 1,
                        "name": "test_name"
                    }
                }
            },
            {
                "id": 40898,
                "timeStamp": "2025-02-20T11:15:09.389118",
                "standingCommitteeId": null,
                "billStatusCode": {
                    "id": 15,
                    "code": "13",
                    "name": "(LC) Draft in Edit",
                    "actionWeight": "HARD",
                    "chamber": "HOUSE",
                    "billProgressCategory": {
                        "id": 2,
                        "code": "10",
                        "description": "In Drafting Process"
                    },
                    "standingCommitteeStatusGrouping": {
                        "id": 1,
                        "name": "test_name"
                    }
                }
            },
            {
                "id": 43207,
                "timeStamp": "2025-02-22T14:20:38.960732",
                "standingCommitteeId": null,
                "billStatusCode": {
                    "id": 19,
                    "code": "17",
                    "name": "(LC) Draft in Input/Proofing",
                    "actionWeight": "HARD",
                    "chamber": "HOUSE",
                    "billProgressCategory": {
                        "id": 2,
                        "code": "10",
                        "description": "In Drafting Process"
                    },
                    "standingCommitteeStatusGrouping": {
                        "id": 1,
                        "name": "test_name"
                    }
                }
            },
            {
                "id": 43399,
                "timeStamp": "2025-02-23T11:43:09.747228",
                "standingCommitteeId": null,
                "billStatusCode": {
                    "id": 20,
                    "code": "18",
                    "name": "(LC) Draft in Final Drafter Review",
                    "actionWeight": "HARD",
                    "chamber": "HOUSE",
                    "billProgressCategory": {
                        "id": 2,
                        "code": "10",
                        "description": "In Drafting Process"
                    },
                    "standingCommitteeStatusGrouping": {
                        "id": 1,
                        "name": "test_name"
                    }
                }
            },
            {
                "id": 43455,
                "timeStamp": "2025-02-23T13:24:25.363963",
                "standingCommitteeId": null,
                "billStatusCode": {
                    "id": 26,
                    "code": "24",
                    "name": "(LC) Draft in Assembly",
                    "actionWeight": "HARD",
                    "chamber": "HOUSE",
                    "billProgressCategory": {
                        "id": 2,
                        "code": "10",
                        "description": "In Drafting Process"
                    },
                    "standingCommitteeStatusGrouping": {
                        "id": 1,
                        "name": "test_name"
                    }
                }
            },
            {
                "id": 44276,
                "timeStamp": "2025-02-24T12:34:37.194624",
                "standingCommitteeId": null,
                "billStatusCode": {
                    "id": 24,
                    "code": "22",
                    "name": "(LC) Draft Ready for Delivery",
                    "actionWeight": "HARD",
                    "chamber": "HOUSE",
                    "billProgressCategory": {
                        "id": 2,
                        "code": "10",
                        "description": "In Drafting Process"
                    },
                    "standingCommitteeStatusGrouping": {
                        "id": 1,
                        "name": "test_name"
                    }
                }
            },
            {
                "id": 45586,
                "timeStamp": "2025-02-25T11:25:30.590842",
                "standingCommitteeId": null,
                "billStatusCode": {
                    "id": 25,
                    "code": "23",
                    "name": "(LC) Draft Delivered to Requester",
                    "actionWeight": "HARD",
                    "chamber": "HOUSE",
                    "billProgressCategory": {
                        "id": 2,
                        "code": "10",
                        "description": "In Drafting Process"
                    },
                    "standingCommitteeStatusGrouping": {
                        "id": 1,
                        "name": "test_name"
                    }
                }
            },
            {
                "id": 47375,
                "timeStamp": "2025-02-26T15:22:52.733967",
                "standingCommitteeId": null,
                "billStatusCode": {
                    "id": 284,
                    "code": "500",
                    "name": "(H) Introduced",
                    "actionWeight": "HARD",
                    "chamber": "HOUSE",
                    "billProgressCategory": {
                        "id": 3,
                        "code": "20",
                        "description": "In First House--Introduced"
                    },
                    "standingCommitteeStatusGrouping": {
                        "id": 1,
                        "name": "test_name"
                    }
                }
            },
            {
                "id": 47786,
                "timeStamp": "2025-02-27T10:20:53.805263",
                "standingCommitteeId": 7,
                "billStatusCode": {
                    "id": 286,
                    "code": "502",
                    "name": "(H) Referred to Committee",
                    "actionWeight": "HARD",
                    "chamber": "HOUSE",
                    "billProgressCategory": {
                        "id": 5,
                        "code": "30",
                        "description": "In First House Committee--Nontabled"
                    },
                    "standingCommitteeStatusGrouping": {
                        "id": 1,
                        "name": "test_name"
                    }
                }
            },
            {
                "id": 47917,
                "timeStamp": "2025-02-27T13:04:46",
                "standingCommitteeId": null,
                "billStatusCode": {
                    "id": 285,
                    "code": "501",
                    "name": "(H) First Reading",
                    "actionWeight": "SOFT",
                    "chamber": "HOUSE",
                    "billProgressCategory": {
                        "id": 3,
                        "code": "20",
                        "description": "In First House--Introduced"
                    },
                    "standingCommitteeStatusGrouping": {
                        "id": 1,
                        "name": "test_name"
                    }
                }
            },
            {
                "id": 48598,
                "timeStamp": "2025-02-28T10:39:56.057202",
                "standingCommitteeId": 7,
                "billStatusCode": {
                    "id": 295,
                    "code": "512",
                    "name": "(H) Hearing",
                    "actionWeight": "HARD",
                    "chamber": "HOUSE",
                    "billProgressCategory": {
                        "id": 5,
                        "code": "30",
                        "description": "In First House Committee--Nontabled"
                    },
                    "standingCommitteeStatusGrouping": {
                        "id": 1,
                        "name": "test_name"
                    }
                }
            },
            {
                "id": 50964,
                "timeStamp": "2025-03-04T09:06:34",
                "standingCommitteeId": 7,
                "billStatusCode": {
                    "id": 307,
                    "code": "524",
                    "name": "(H) Tabled in Committee",
                    "actionWeight": "HARD",
                    "chamber": "HOUSE",
                    "billProgressCategory": {
                        "id": 4,
                        "code": "25",
                        "description": "In First House Committee--Tabled"
                    },
                    "standingCommitteeStatusGrouping": {
                        "id": 1,
                        "name": "test_name"
                    }
                }
            },
            {
                "id": 54077,
                "timeStamp": "2025-03-12T13:00:00",
                "standingCommitteeId": null,
                "billStatusCode": {
                    "id": 446,
                    "code": "667",
                    "name": "(H) Missed Deadline for General Bill Transmittal",
                    "actionWeight": "HARD",
                    "chamber": "HOUSE",
                    "billProgressCategory": {
                        "id": 1,
                        "code": "0",
                        "description": "Probably Dead"
                    },
                    "standingCommitteeStatusGrouping": {
                        "id": 1,
                        "name": "test_name"
                    }
                }
            },
            {
                "id": 89078,
                "timeStamp": "2025-05-20T11:00:00",
                "standingCommitteeId": null,
                "billStatusCode": {
                    "id": 454,
                    "code": "675",
                    "name": "(H) Died in Process",
                    "actionWeight": "HARD",
                    "chamber": "HOUSE",
                    "billProgressCategory": {
                        "id": 1,
                        "code": "0",
                        "description": "Probably Dead"
                    },
                    "standingCommitteeStatusGrouping": {
                        "id": 1,
                        "name": "test_name"
                    }
                }
            }
        ],
        "legalNote": false,
        "sessionId": 2,
        "fiscalNote": false,
        "fiscalAnalystId": null,
        "preIntroRequired": false,
        "subjects": [
            {
                "id": 61538,
                "subjectCode": {
                    "id": 53,
                    "code": "ENER",
                    "description": "Energy",
                    "revenueAndAprops": null,
                    "voteMajorityType": "SIMPLE",
                    "primary": true
                }
            },
            {
                "id": 85574,
                "subjectCode": {
                    "id": 170,
                    "code": "UT",
                    "description": "Utilities",
                    "revenueAndAprops": null,
                    "voteMajorityType": "SIMPLE",
                    "primary": true
                }
            }
        ],
        "byRequestOfs": []
    },
    "enrolled": null,
    "versionNumber": 1,
    "sessionId": 2
}