{
    "id": 1638,
    "deadlineCodeId": 5,
    "billNumber": 150,
    "sessionLawChapterNumber": null,
    "sponsorId": 161,
    "carrierId": null,
    "drafterStaffMemberId": 127,
    "billType": {
        "id": 4,
        "description": "Senate Bill",
        "code": "SB",
        "sortOrder": 3,
        "chamber": "SENATE"
    },
    "affectedMcaBillSections": [],
    "sessionLawEffectiveDates": [],
    "draft": {
        "id": 1638,
        "draftNumber": "LC1639",
        "date": "2025-01-14T13:27:35",
        "shortTitle": "Generally revise alcohol and tobacco laws",
        "description": null,
        "requesterId": 161,
        "requesterType": "LEGISLATOR",
        "billStatuses": [
            {
                "id": 3702,
                "timeStamp": "2024-11-19T07:55:50.918724",
                "standingCommitteeId": null,
                "billStatusCode": {
                    "id": 5,
                    "code": "1",
                    "name": "(LC) Drafter Assigned",
                    "actionWeight": "HARD",
                    "chamber": "HOUSE",
                    "billProgressCategory": {
                        "id": 2,
                        "code": "10",
                        "description": "In Drafting Process"
                    },
                    "standingCommitteeStatusGrouping": {
                        "id": 1,
                        "name": "test_name"
                    }
                }
            },
            {
                "id": 13781,
                "timeStamp": "2025-01-06T07:28:03.230787",
                "standingCommitteeId": null,
                "billStatusCode": {
                    "id": 14,
                    "code": "12",
                    "name": "(LC) Draft in Legal Review",
                    "actionWeight": "HARD",
                    "chamber": "HOUSE",
                    "billProgressCategory": {
                        "id": 2,
                        "code": "10",
                        "description": "In Drafting Process"
                    },
                    "standingCommitteeStatusGrouping": {
                        "id": 1,
                        "name": "test_name"
                    }
                }
            },
            {
                "id": 13845,
                "timeStamp": "2025-01-06T08:51:01.09112",
                "standingCommitteeId": null,
                "billStatusCode": {
                    "id": 15,
                    "code": "13",
                    "name": "(LC) Draft in Edit",
                    "actionWeight": "HARD",
                    "chamber": "HOUSE",
                    "billProgressCategory": {
                        "id": 2,
                        "code": "10",
                        "description": "In Drafting Process"
                    },
                    "standingCommitteeStatusGrouping": {
                        "id": 1,
                        "name": "test_name"
                    }
                }
            },
            {
                "id": 16381,
                "timeStamp": "2025-01-10T14:21:49.247065",
                "standingCommitteeId": null,
                "billStatusCode": {
                    "id": 19,
                    "code": "17",
                    "name": "(LC) Draft in Input/Proofing",
                    "actionWeight": "HARD",
                    "chamber": "HOUSE",
                    "billProgressCategory": {
                        "id": 2,
                        "code": "10",
                        "description": "In Drafting Process"
                    },
                    "standingCommitteeStatusGrouping": {
                        "id": 1,
                        "name": "test_name"
                    }
                }
            },
            {
                "id": 16696,
                "timeStamp": "2025-01-12T09:14:02.508288",
                "standingCommitteeId": null,
                "billStatusCode": {
                    "id": 20,
                    "code": "18",
                    "name": "(LC) Draft in Final Drafter Review",
                    "actionWeight": "HARD",
                    "chamber": "HOUSE",
                    "billProgressCategory": {
                        "id": 2,
                        "code": "10",
                        "description": "In Drafting Process"
                    },
                    "standingCommitteeStatusGrouping": {
                        "id": 1,
                        "name": "test_name"
                    }
                }
            },
            {
                "id": 16701,
                "timeStamp": "2025-01-12T11:50:37.987301",
                "standingCommitteeId": null,
                "billStatusCode": {
                    "id": 26,
                    "code": "24",
                    "name": "(LC) Draft in Assembly",
                    "actionWeight": "HARD",
                    "chamber": "HOUSE",
                    "billProgressCategory": {
                        "id": 2,
                        "code": "10",
                        "description": "In Drafting Process"
                    },
                    "standingCommitteeStatusGrouping": {
                        "id": 1,
                        "name": "test_name"
                    }
                }
            },
            {
                "id": 17463,
                "timeStamp": "2025-01-14T13:27:35.143031",
                "standingCommitteeId": null,
                "billStatusCode": {
                    "id": 25,
                    "code": "23",
                    "name": "(LC) Draft Delivered to Requester",
                    "actionWeight": "HARD",
                    "chamber": "HOUSE",
                    "billProgressCategory": {
                        "id": 2,
                        "code": "10",
                        "description": "In Drafting Process"
                    },
                    "standingCommitteeStatusGrouping": {
                        "id": 1,
                        "name": "test_name"
                    }
                }
            },
            {
                "id": 17531,
                "timeStamp": "2025-01-14T14:48:54.66972",
                "standingCommitteeId": null,
                "billStatusCode": {
                    "id": 52,
                    "code": "100",
                    "name": "(S) Introduced",
                    "actionWeight": "HARD",
                    "chamber": "SENATE",
                    "billProgressCategory": {
                        "id": 3,
                        "code": "20",
                        "description": "In First House--Introduced"
                    },
                    "standingCommitteeStatusGrouping": {
                        "id": 1,
                        "name": "test_name"
                    }
                }
            }
        ],
        "legalNote": false,
        "sessionId": 2,
        "fiscalNote": true,
        "fiscalAnalystId": null,
        "preIntroRequired": false,
        "subjects": [
            {
                "id": 2763,
                "subjectCode": {
                    "id": 21,
                    "code": "CIG",
                    "description": "Cigarettes and Tobacco",
                    "revenueAndAprops": null,
                    "voteMajorityType": "SIMPLE",
                    "primary": true
                }
            },
            {
                "id": 84241,
                "subjectCode": {
                    "id": 121,
                    "code": "REVS",
                    "description": "Revenue, State",
                    "revenueAndAprops": "REVENUE",
                    "voteMajorityType": "SIMPLE",
                    "primary": true
                }
            }
        ],
        "byRequestOfs": []
    },
    "enrolled": null,
    "versionNumber": 1,
    "sessionId": 2
}