{
    "id": 63,
    "deadlineCodeId": 3,
    "billNumber": 154,
    "sessionLawChapterNumber": null,
    "sponsorId": 76,
    "carrierId": null,
    "drafterStaffMemberId": 107,
    "billType": {
        "id": 4,
        "description": "Senate Bill",
        "code": "SB",
        "sortOrder": 3,
        "chamber": "SENATE"
    },
    "affectedMcaBillSections": [],
    "sessionLawEffectiveDates": [],
    "draft": {
        "id": 63,
        "draftNumber": "LC0060",
        "date": "2025-01-15T11:31:08",
        "shortTitle": "Revise prohibition on sale or purchase of human body parts under the revised Uniform Anatomical Gift Act.",
        "description": null,
        "requesterId": 76,
        "requesterType": "LEGISLATOR",
        "billStatuses": [
            {
                "id": 65,
                "timeStamp": "2024-08-28T07:48:47.088441",
                "standingCommitteeId": null,
                "billStatusCode": {
                    "id": 5,
                    "code": "1",
                    "name": "(LC) Drafter Assigned",
                    "actionWeight": "HARD",
                    "chamber": "HOUSE",
                    "billProgressCategory": {
                        "id": 2,
                        "code": "10",
                        "description": "In Drafting Process"
                    },
                    "standingCommitteeStatusGrouping": {
                        "id": 1,
                        "name": "test_name"
                    }
                }
            },
            {
                "id": 13521,
                "timeStamp": "2025-01-03T13:37:36.493173",
                "standingCommitteeId": null,
                "billStatusCode": {
                    "id": 14,
                    "code": "12",
                    "name": "(LC) Draft in Legal Review",
                    "actionWeight": "HARD",
                    "chamber": "HOUSE",
                    "billProgressCategory": {
                        "id": 2,
                        "code": "10",
                        "description": "In Drafting Process"
                    },
                    "standingCommitteeStatusGrouping": {
                        "id": 1,
                        "name": "test_name"
                    }
                }
            },
            {
                "id": 14467,
                "timeStamp": "2025-01-07T09:03:16.06649",
                "standingCommitteeId": null,
                "billStatusCode": {
                    "id": 15,
                    "code": "13",
                    "name": "(LC) Draft in Edit",
                    "actionWeight": "HARD",
                    "chamber": "HOUSE",
                    "billProgressCategory": {
                        "id": 2,
                        "code": "10",
                        "description": "In Drafting Process"
                    },
                    "standingCommitteeStatusGrouping": {
                        "id": 1,
                        "name": "test_name"
                    }
                }
            },
            {
                "id": 15137,
                "timeStamp": "2025-01-08T08:58:49.135845",
                "standingCommitteeId": null,
                "billStatusCode": {
                    "id": 19,
                    "code": "17",
                    "name": "(LC) Draft in Input/Proofing",
                    "actionWeight": "HARD",
                    "chamber": "HOUSE",
                    "billProgressCategory": {
                        "id": 2,
                        "code": "10",
                        "description": "In Drafting Process"
                    },
                    "standingCommitteeStatusGrouping": {
                        "id": 1,
                        "name": "test_name"
                    }
                }
            },
            {
                "id": 15306,
                "timeStamp": "2025-01-08T11:17:46.67431",
                "standingCommitteeId": null,
                "billStatusCode": {
                    "id": 20,
                    "code": "18",
                    "name": "(LC) Draft in Final Drafter Review",
                    "actionWeight": "HARD",
                    "chamber": "HOUSE",
                    "billProgressCategory": {
                        "id": 2,
                        "code": "10",
                        "description": "In Drafting Process"
                    },
                    "standingCommitteeStatusGrouping": {
                        "id": 1,
                        "name": "test_name"
                    }
                }
            },
            {
                "id": 15790,
                "timeStamp": "2025-01-09T13:57:49.277417",
                "standingCommitteeId": null,
                "billStatusCode": {
                    "id": 26,
                    "code": "24",
                    "name": "(LC) Draft in Assembly",
                    "actionWeight": "HARD",
                    "chamber": "HOUSE",
                    "billProgressCategory": {
                        "id": 2,
                        "code": "10",
                        "description": "In Drafting Process"
                    },
                    "standingCommitteeStatusGrouping": {
                        "id": 1,
                        "name": "test_name"
                    }
                }
            },
            {
                "id": 17133,
                "timeStamp": "2025-01-13T16:43:55.868147",
                "standingCommitteeId": null,
                "billStatusCode": {
                    "id": 24,
                    "code": "22",
                    "name": "(LC) Draft Ready for Delivery",
                    "actionWeight": "HARD",
                    "chamber": "HOUSE",
                    "billProgressCategory": {
                        "id": 2,
                        "code": "10",
                        "description": "In Drafting Process"
                    },
                    "standingCommitteeStatusGrouping": {
                        "id": 1,
                        "name": "test_name"
                    }
                }
            },
            {
                "id": 17807,
                "timeStamp": "2025-01-15T11:31:08.929422",
                "standingCommitteeId": null,
                "billStatusCode": {
                    "id": 25,
                    "code": "23",
                    "name": "(LC) Draft Delivered to Requester",
                    "actionWeight": "HARD",
                    "chamber": "HOUSE",
                    "billProgressCategory": {
                        "id": 2,
                        "code": "10",
                        "description": "In Drafting Process"
                    },
                    "standingCommitteeStatusGrouping": {
                        "id": 1,
                        "name": "test_name"
                    }
                }
            },
            {
                "id": 17895,
                "timeStamp": "2025-01-15T12:40:54.165909",
                "standingCommitteeId": null,
                "billStatusCode": {
                    "id": 52,
                    "code": "100",
                    "name": "(S) Introduced",
                    "actionWeight": "HARD",
                    "chamber": "SENATE",
                    "billProgressCategory": {
                        "id": 3,
                        "code": "20",
                        "description": "In First House--Introduced"
                    },
                    "standingCommitteeStatusGrouping": {
                        "id": 1,
                        "name": "test_name"
                    }
                }
            }
        ],
        "legalNote": false,
        "sessionId": 2,
        "fiscalNote": false,
        "fiscalAnalystId": null,
        "preIntroRequired": false,
        "subjects": [
            {
                "id": 120,
                "subjectCode": {
                    "id": 1,
                    "code": "ABOR",
                    "description": "Abortion",
                    "revenueAndAprops": null,
                    "voteMajorityType": "SIMPLE",
                    "primary": true
                }
            },
            {
                "id": 121,
                "subjectCode": {
                    "id": 36,
                    "code": "CR",
                    "description": "Crimes",
                    "revenueAndAprops": null,
                    "voteMajorityType": "SIMPLE",
                    "primary": true
                }
            },
            {
                "id": 122,
                "subjectCode": {
                    "id": 68,
                    "code": "HLTH",
                    "description": "Health (see also: Health Care Services; Safety)",
                    "revenueAndAprops": null,
                    "voteMajorityType": "SIMPLE",
                    "primary": true
                }
            },
            {
                "id": 123,
                "subjectCode": {
                    "id": 124,
                    "code": "SAF",
                    "description": "Safety  (see also: Health)",
                    "revenueAndAprops": null,
                    "voteMajorityType": "SIMPLE",
                    "primary": true
                }
            },
            {
                "id": 646,
                "subjectCode": {
                    "id": 67,
                    "code": "HLTC",
                    "description": "Health Care Services (see also: Health)",
                    "revenueAndAprops": null,
                    "voteMajorityType": "SIMPLE",
                    "primary": true
                }
            }
        ],
        "byRequestOfs": []
    },
    "enrolled": null,
    "versionNumber": 1,
    "sessionId": 2
}