[
    {
        "id": 1583,
        "motion": "Do Pass",
        "orderOfBusinessId": 7,
        "dateTime": "2025-03-04T18:41:43",
        "sessionId": 2,
        "amendmentNumber": null,
        "bill": {
            "id": 1386,
            "deadlineCodeId": 3,
            "billNumber": 565,
            "sessionLawChapterNumber": null,
            "sponsorId": 104,
            "carrierId": null,
            "drafterStaffMemberId": 127,
            "enrolled": null,
            "versionNumber": 1,
            "sessionId": 2
        },
        "legislatorVotes": [
            {
                "id": 119093,
                "legislatorId": 4,
                "voteType": "YES",
                "votingMemberStatus": null
            },
            {
                "id": 119070,
                "legislatorId": 6,
                "voteType": "YES",
                "votingMemberStatus": null
            },
            {
                "id": 119056,
                "legislatorId": 10,
                "voteType": "YES",
                "votingMemberStatus": null
            },
            {
                "id": 119113,
                "legislatorId": 16,
                "voteType": "NO",
                "votingMemberStatus": null
            },
            {
                "id": 119126,
                "legislatorId": 27,
                "voteType": "NO",
                "votingMemberStatus": null
            },
            {
                "id": 119120,
                "legislatorId": 38,
                "voteType": "NO",
                "votingMemberStatus": null
            },
            {
                "id": 119144,
                "legislatorId": 43,
                "voteType": "NO",
                "votingMemberStatus": null
            },
            {
                "id": 119149,
                "legislatorId": 47,
                "voteType": "NO",
                "votingMemberStatus": null
            },
            {
                "id": 119104,
                "legislatorId": 49,
                "voteType": "NO",
                "votingMemberStatus": null
            },
            {
                "id": 119114,
                "legislatorId": 50,
                "voteType": "NO",
                "votingMemberStatus": null
            },
            {
                "id": 119071,
                "legislatorId": 51,
                "voteType": "YES",
                "votingMemberStatus": null
            },
            {
                "id": 119055,
                "legislatorId": 53,
                "voteType": "YES",
                "votingMemberStatus": null
            },
            {
                "id": 119116,
                "legislatorId": 56,
                "voteType": "NO",
                "votingMemberStatus": null
            },
            {
                "id": 119133,
                "legislatorId": 57,
                "voteType": "NO",
                "votingMemberStatus": null
            },
            {
                "id": 119150,
                "legislatorId": 59,
                "voteType": "NO",
                "votingMemberStatus": null
            },
            {
                "id": 119089,
                "legislatorId": 60,
                "voteType": "YES",
                "votingMemberStatus": null
            },
            {
                "id": 119102,
                "legislatorId": 61,
                "voteType": "NO",
                "votingMemberStatus": null
            },
            {
                "id": 119117,
                "legislatorId": 63,
                "voteType": "NO",
                "votingMemberStatus": null
            },
            {
                "id": 119128,
                "legislatorId": 66,
                "voteType": "NO",
                "votingMemberStatus": null
            },
            {
                "id": 119146,
                "legislatorId": 67,
                "voteType": "NO",
                "votingMemberStatus": null
            },
            {
                "id": 119141,
                "legislatorId": 68,
                "voteType": "NO",
                "votingMemberStatus": null
            },
            {
                "id": 119135,
                "legislatorId": 69,
                "voteType": "NO",
                "votingMemberStatus": null
            },
            {
                "id": 119143,
                "legislatorId": 71,
                "voteType": "NO",
                "votingMemberStatus": null
            },
            {
                "id": 119058,
                "legislatorId": 72,
                "voteType": "YES",
                "votingMemberStatus": null
            },
            {
                "id": 119074,
                "legislatorId": 73,
                "voteType": "YES",
                "votingMemberStatus": null
            },
            {
                "id": 119119,
                "legislatorId": 75,
                "voteType": "NO",
                "votingMemberStatus": null
            },
            {
                "id": 119053,
                "legislatorId": 77,
                "voteType": "YES",
                "votingMemberStatus": null
            },
            {
                "id": 119121,
                "legislatorId": 79,
                "voteType": "NO",
                "votingMemberStatus": null
            },
            {
                "id": 119092,
                "legislatorId": 82,
                "voteType": "YES",
                "votingMemberStatus": null
            },
            {
                "id": 119122,
                "legislatorId": 83,
                "voteType": "NO",
                "votingMemberStatus": null
            },
            {
                "id": 119063,
                "legislatorId": 84,
                "voteType": "YES",
                "votingMemberStatus": null
            },
            {
                "id": 119100,
                "legislatorId": 86,
                "voteType": "NO",
                "votingMemberStatus": null
            },
            {
                "id": 119136,
                "legislatorId": 96,
                "voteType": "NO",
                "votingMemberStatus": null
            },
            {
                "id": 119145,
                "legislatorId": 98,
                "voteType": "NO",
                "votingMemberStatus": null
            },
            {
                "id": 119137,
                "legislatorId": 99,
                "voteType": "NO",
                "votingMemberStatus": null
            },
            {
                "id": 119077,
                "legislatorId": 100,
                "voteType": "YES",
                "votingMemberStatus": null
            },
            {
                "id": 119106,
                "legislatorId": 102,
                "voteType": "NO",
                "votingMemberStatus": null
            },
            {
                "id": 119148,
                "legislatorId": 103,
                "voteType": "NO",
                "votingMemberStatus": null
            },
            {
                "id": 119094,
                "legislatorId": 104,
                "voteType": "YES",
                "votingMemberStatus": null
            },
            {
                "id": 119107,
                "legislatorId": 105,
                "voteType": "NO",
                "votingMemberStatus": null
            },
            {
                "id": 119086,
                "legislatorId": 106,
                "voteType": "YES",
                "votingMemberStatus": null
            },
            {
                "id": 119110,
                "legislatorId": 109,
                "voteType": "NO",
                "votingMemberStatus": null
            },
            {
                "id": 119129,
                "legislatorId": 111,
                "voteType": "NO",
                "votingMemberStatus": null
            },
            {
                "id": 119134,
                "legislatorId": 112,
                "voteType": "NO",
                "votingMemberStatus": null
            },
            {
                "id": 119095,
                "legislatorId": 115,
                "voteType": "YES",
                "votingMemberStatus": null
            },
            {
                "id": 119081,
                "legislatorId": 116,
                "voteType": "YES",
                "votingMemberStatus": null
            },
            {
                "id": 119088,
                "legislatorId": 117,
                "voteType": "YES",
                "votingMemberStatus": null
            },
            {
                "id": 119140,
                "legislatorId": 119,
                "voteType": "NO",
                "votingMemberStatus": null
            },
            {
                "id": 119052,
                "legislatorId": 121,
                "voteType": "YES",
                "votingMemberStatus": null
            },
            {
                "id": 119075,
                "legislatorId": 134,
                "voteType": "YES",
                "votingMemberStatus": null
            },
            {
                "id": 119061,
                "legislatorId": 136,
                "voteType": "YES",
                "votingMemberStatus": null
            },
            {
                "id": 119062,
                "legislatorId": 138,
                "voteType": "YES",
                "votingMemberStatus": null
            },
            {
                "id": 119051,
                "legislatorId": 139,
                "voteType": "ABSENT",
                "votingMemberStatus": null
            },
            {
                "id": 119060,
                "legislatorId": 140,
                "voteType": "YES",
                "votingMemberStatus": null
            },
            {
                "id": 119112,
                "legislatorId": 142,
                "voteType": "NO",
                "votingMemberStatus": null
            },
            {
                "id": 119147,
                "legislatorId": 143,
                "voteType": "NO",
                "votingMemberStatus": null
            },
            {
                "id": 119082,
                "legislatorId": 144,
                "voteType": "YES",
                "votingMemberStatus": null
            },
            {
                "id": 119073,
                "legislatorId": 146,
                "voteType": "YES",
                "votingMemberStatus": null
            },
            {
                "id": 119078,
                "legislatorId": 147,
                "voteType": "YES",
                "votingMemberStatus": null
            },
            {
                "id": 119125,
                "legislatorId": 148,
                "voteType": "NO",
                "votingMemberStatus": null
            },
            {
                "id": 119069,
                "legislatorId": 156,
                "voteType": "YES",
                "votingMemberStatus": null
            },
            {
                "id": 119132,
                "legislatorId": 157,
                "voteType": "NO",
                "votingMemberStatus": null
            },
            {
                "id": 119118,
                "legislatorId": 158,
                "voteType": "NO",
                "votingMemberStatus": null
            },
            {
                "id": 119111,
                "legislatorId": 159,
                "voteType": "NO",
                "votingMemberStatus": null
            },
            {
                "id": 119083,
                "legislatorId": 163,
                "voteType": "YES",
                "votingMemberStatus": null
            },
            {
                "id": 119101,
                "legislatorId": 174,
                "voteType": "NO",
                "votingMemberStatus": null
            },
            {
                "id": 119057,
                "legislatorId": 175,
                "voteType": "YES",
                "votingMemberStatus": null
            },
            {
                "id": 119097,
                "legislatorId": 176,
                "voteType": "YES",
                "votingMemberStatus": null
            },
            {
                "id": 119085,
                "legislatorId": 177,
                "voteType": "YES",
                "votingMemberStatus": null
            },
            {
                "id": 119091,
                "legislatorId": 178,
                "voteType": "YES",
                "votingMemberStatus": null
            },
            {
                "id": 119080,
                "legislatorId": 179,
                "voteType": "YES",
                "votingMemberStatus": null
            },
            {
                "id": 119054,
                "legislatorId": 180,
                "voteType": "YES",
                "votingMemberStatus": null
            },
            {
                "id": 119139,
                "legislatorId": 181,
                "voteType": "NO",
                "votingMemberStatus": null
            },
            {
                "id": 119138,
                "legislatorId": 182,
                "voteType": "NO",
                "votingMemberStatus": null
            },
            {
                "id": 119123,
                "legislatorId": 183,
                "voteType": "NO",
                "votingMemberStatus": null
            },
            {
                "id": 119084,
                "legislatorId": 184,
                "voteType": "YES",
                "votingMemberStatus": null
            },
            {
                "id": 119068,
                "legislatorId": 185,
                "voteType": "YES",
                "votingMemberStatus": null
            },
            {
                "id": 119109,
                "legislatorId": 186,
                "voteType": "NO",
                "votingMemberStatus": null
            },
            {
                "id": 119076,
                "legislatorId": 197,
                "voteType": "YES",
                "votingMemberStatus": null
            },
            {
                "id": 119099,
                "legislatorId": 199,
                "voteType": "NO",
                "votingMemberStatus": null
            },
            {
                "id": 119124,
                "legislatorId": 200,
                "voteType": "NO",
                "votingMemberStatus": null
            },
            {
                "id": 119079,
                "legislatorId": 201,
                "voteType": "YES",
                "votingMemberStatus": null
            },
            {
                "id": 119131,
                "legislatorId": 202,
                "voteType": "NO",
                "votingMemberStatus": null
            },
            {
                "id": 119096,
                "legislatorId": 223,
                "voteType": "YES",
                "votingMemberStatus": null
            },
            {
                "id": 119108,
                "legislatorId": 225,
                "voteType": "NO",
                "votingMemberStatus": null
            },
            {
                "id": 119130,
                "legislatorId": 226,
                "voteType": "NO",
                "votingMemberStatus": null
            },
            {
                "id": 119105,
                "legislatorId": 227,
                "voteType": "NO",
                "votingMemberStatus": null
            },
            {
                "id": 119072,
                "legislatorId": 228,
                "voteType": "YES",
                "votingMemberStatus": null
            },
            {
                "id": 119115,
                "legislatorId": 230,
                "voteType": "NO",
                "votingMemberStatus": null
            },
            {
                "id": 119064,
                "legislatorId": 231,
                "voteType": "YES",
                "votingMemberStatus": null
            },
            {
                "id": 119127,
                "legislatorId": 232,
                "voteType": "NO",
                "votingMemberStatus": null
            },
            {
                "id": 119090,
                "legislatorId": 233,
                "voteType": "YES",
                "votingMemberStatus": null
            },
            {
                "id": 119066,
                "legislatorId": 234,
                "voteType": "YES",
                "votingMemberStatus": null
            },
            {
                "id": 119065,
                "legislatorId": 236,
                "voteType": "YES",
                "votingMemberStatus": null
            },
            {
                "id": 119067,
                "legislatorId": 237,
                "voteType": "YES",
                "votingMemberStatus": null
            },
            {
                "id": 119087,
                "legislatorId": 240,
                "voteType": "YES",
                "votingMemberStatus": null
            },
            {
                "id": 119103,
                "legislatorId": 241,
                "voteType": "NO",
                "votingMemberStatus": null
            },
            {
                "id": 119142,
                "legislatorId": 272,
                "voteType": "NO",
                "votingMemberStatus": null
            },
            {
                "id": 119098,
                "legislatorId": 293,
                "voteType": "YES",
                "votingMemberStatus": null
            },
            {
                "id": 119059,
                "legislatorId": 304,
                "voteType": "YES",
                "votingMemberStatus": null
            }
        ],
        "billStatus": {
            "id": 51757,
            "timeStamp": "2025-03-04T18:42:00",
            "standingCommitteeId": null
        },
        "systemId": {
            "chamber": "HOUSE",
            "sequence": 960
        }
    },
    {
        "id": 1816,
        "motion": "ReconsAction - Stafman",
        "orderOfBusinessId": 15,
        "dateTime": "2025-03-05T20:02:27",
        "sessionId": 2,
        "amendmentNumber": null,
        "bill": {
            "id": 1386,
            "deadlineCodeId": 3,
            "billNumber": 565,
            "sessionLawChapterNumber": null,
            "sponsorId": 104,
            "carrierId": null,
            "drafterStaffMemberId": 127,
            "enrolled": null,
            "versionNumber": 1,
            "sessionId": 2
        },
        "legislatorVotes": [
            {
                "id": 137593,
                "legislatorId": 4,
                "voteType": "YES",
                "votingMemberStatus": null
            },
            {
                "id": 137570,
                "legislatorId": 6,
                "voteType": "YES",
                "votingMemberStatus": null
            },
            {
                "id": 137564,
                "legislatorId": 10,
                "voteType": "YES",
                "votingMemberStatus": null
            },
            {
                "id": 137607,
                "legislatorId": 16,
                "voteType": "NO",
                "votingMemberStatus": null
            },
            {
                "id": 137648,
                "legislatorId": 27,
                "voteType": "NO",
                "votingMemberStatus": null
            },
            {
                "id": 137616,
                "legislatorId": 38,
                "voteType": "NO",
                "votingMemberStatus": null
            },
            {
                "id": 137640,
                "legislatorId": 43,
                "voteType": "NO",
                "votingMemberStatus": null
            },
            {
                "id": 137645,
                "legislatorId": 47,
                "voteType": "NO",
                "votingMemberStatus": null
            },
            {
                "id": 137599,
                "legislatorId": 49,
                "voteType": "NO",
                "votingMemberStatus": null
            },
            {
                "id": 137608,
                "legislatorId": 50,
                "voteType": "NO",
                "votingMemberStatus": null
            },
            {
                "id": 137571,
                "legislatorId": 51,
                "voteType": "YES",
                "votingMemberStatus": null
            },
            {
                "id": 137563,
                "legislatorId": 53,
                "voteType": "YES",
                "votingMemberStatus": null
            },
            {
                "id": 137610,
                "legislatorId": 56,
                "voteType": "NO",
                "votingMemberStatus": null
            },
            {
                "id": 137551,
                "legislatorId": 57,
                "voteType": "ABSENT",
                "votingMemberStatus": null
            },
            {
                "id": 137634,
                "legislatorId": 59,
                "voteType": "NO",
                "votingMemberStatus": null
            },
            {
                "id": 137589,
                "legislatorId": 60,
                "voteType": "YES",
                "votingMemberStatus": null
            },
            {
                "id": 137597,
                "legislatorId": 61,
                "voteType": "NO",
                "votingMemberStatus": null
            },
            {
                "id": 137611,
                "legislatorId": 63,
                "voteType": "NO",
                "votingMemberStatus": null
            },
            {
                "id": 137553,
                "legislatorId": 66,
                "voteType": "YES",
                "votingMemberStatus": null
            },
            {
                "id": 137642,
                "legislatorId": 67,
                "voteType": "NO",
                "votingMemberStatus": null
            },
            {
                "id": 137637,
                "legislatorId": 68,
                "voteType": "NO",
                "votingMemberStatus": null
            },
            {
                "id": 137614,
                "legislatorId": 69,
                "voteType": "NO",
                "votingMemberStatus": null
            },
            {
                "id": 137639,
                "legislatorId": 71,
                "voteType": "NO",
                "votingMemberStatus": null
            },
            {
                "id": 137566,
                "legislatorId": 72,
                "voteType": "YES",
                "votingMemberStatus": null
            },
            {
                "id": 137574,
                "legislatorId": 73,
                "voteType": "YES",
                "votingMemberStatus": null
            },
            {
                "id": 137615,
                "legislatorId": 75,
                "voteType": "NO",
                "votingMemberStatus": null
            },
            {
                "id": 137613,
                "legislatorId": 77,
                "voteType": "NO",
                "votingMemberStatus": null
            },
            {
                "id": 137617,
                "legislatorId": 79,
                "voteType": "NO",
                "votingMemberStatus": null
            },
            {
                "id": 137592,
                "legislatorId": 82,
                "voteType": "YES",
                "votingMemberStatus": null
            },
            {
                "id": 137618,
                "legislatorId": 83,
                "voteType": "NO",
                "votingMemberStatus": null
            },
            {
                "id": 137558,
                "legislatorId": 84,
                "voteType": "YES",
                "votingMemberStatus": null
            },
            {
                "id": 137595,
                "legislatorId": 86,
                "voteType": "NO",
                "votingMemberStatus": null
            },
            {
                "id": 137626,
                "legislatorId": 96,
                "voteType": "NO",
                "votingMemberStatus": null
            },
            {
                "id": 137641,
                "legislatorId": 98,
                "voteType": "NO",
                "votingMemberStatus": null
            },
            {
                "id": 137627,
                "legislatorId": 99,
                "voteType": "NO",
                "votingMemberStatus": null
            },
            {
                "id": 137577,
                "legislatorId": 100,
                "voteType": "YES",
                "votingMemberStatus": null
            },
            {
                "id": 137646,
                "legislatorId": 102,
                "voteType": "NO",
                "votingMemberStatus": null
            },
            {
                "id": 137644,
                "legislatorId": 103,
                "voteType": "NO",
                "votingMemberStatus": null
            },
            {
                "id": 137594,
                "legislatorId": 104,
                "voteType": "YES",
                "votingMemberStatus": null
            },
            {
                "id": 137601,
                "legislatorId": 105,
                "voteType": "NO",
                "votingMemberStatus": null
            },
            {
                "id": 137586,
                "legislatorId": 106,
                "voteType": "YES",
                "votingMemberStatus": null
            },
            {
                "id": 137604,
                "legislatorId": 109,
                "voteType": "NO",
                "votingMemberStatus": null
            },
            {
                "id": 137622,
                "legislatorId": 111,
                "voteType": "NO",
                "votingMemberStatus": null
            },
            {
                "id": 137633,
                "legislatorId": 112,
                "voteType": "NO",
                "votingMemberStatus": null
            },
            {
                "id": 137554,
                "legislatorId": 115,
                "voteType": "YES",
                "votingMemberStatus": null
            },
            {
                "id": 137581,
                "legislatorId": 116,
                "voteType": "YES",
                "votingMemberStatus": null
            },
            {
                "id": 137588,
                "legislatorId": 117,
                "voteType": "YES",
                "votingMemberStatus": null
            },
            {
                "id": 137636,
                "legislatorId": 119,
                "voteType": "NO",
                "votingMemberStatus": null
            },
            {
                "id": 137635,
                "legislatorId": 121,
                "voteType": "NO",
                "votingMemberStatus": null
            },
            {
                "id": 137575,
                "legislatorId": 134,
                "voteType": "YES",
                "votingMemberStatus": null
            },
            {
                "id": 137569,
                "legislatorId": 136,
                "voteType": "YES",
                "votingMemberStatus": null
            },
            {
                "id": 137621,
                "legislatorId": 138,
                "voteType": "NO",
                "votingMemberStatus": null
            },
            {
                "id": 137552,
                "legislatorId": 139,
                "voteType": "ABSENT",
                "votingMemberStatus": null
            },
            {
                "id": 137568,
                "legislatorId": 140,
                "voteType": "YES",
                "votingMemberStatus": null
            },
            {
                "id": 137606,
                "legislatorId": 142,
                "voteType": "NO",
                "votingMemberStatus": null
            },
            {
                "id": 137643,
                "legislatorId": 143,
                "voteType": "NO",
                "votingMemberStatus": null
            },
            {
                "id": 137582,
                "legislatorId": 144,
                "voteType": "YES",
                "votingMemberStatus": null
            },
            {
                "id": 137573,
                "legislatorId": 146,
                "voteType": "YES",
                "votingMemberStatus": null
            },
            {
                "id": 137578,
                "legislatorId": 147,
                "voteType": "YES",
                "votingMemberStatus": null
            },
            {
                "id": 137647,
                "legislatorId": 148,
                "voteType": "NO",
                "votingMemberStatus": null
            },
            {
                "id": 137630,
                "legislatorId": 156,
                "voteType": "NO",
                "votingMemberStatus": null
            },
            {
                "id": 137625,
                "legislatorId": 157,
                "voteType": "NO",
                "votingMemberStatus": null
            },
            {
                "id": 137612,
                "legislatorId": 158,
                "voteType": "NO",
                "votingMemberStatus": null
            },
            {
                "id": 137605,
                "legislatorId": 159,
                "voteType": "NO",
                "votingMemberStatus": null
            },
            {
                "id": 137583,
                "legislatorId": 163,
                "voteType": "YES",
                "votingMemberStatus": null
            },
            {
                "id": 137596,
                "legislatorId": 174,
                "voteType": "NO",
                "votingMemberStatus": null
            },
            {
                "id": 137565,
                "legislatorId": 175,
                "voteType": "YES",
                "votingMemberStatus": null
            },
            {
                "id": 137556,
                "legislatorId": 176,
                "voteType": "YES",
                "votingMemberStatus": null
            },
            {
                "id": 137585,
                "legislatorId": 177,
                "voteType": "YES",
                "votingMemberStatus": null
            },
            {
                "id": 137591,
                "legislatorId": 178,
                "voteType": "YES",
                "votingMemberStatus": null
            },
            {
                "id": 137580,
                "legislatorId": 179,
                "voteType": "YES",
                "votingMemberStatus": null
            },
            {
                "id": 137632,
                "legislatorId": 180,
                "voteType": "NO",
                "votingMemberStatus": null
            },
            {
                "id": 137629,
                "legislatorId": 181,
                "voteType": "NO",
                "votingMemberStatus": null
            },
            {
                "id": 137628,
                "legislatorId": 182,
                "voteType": "NO",
                "votingMemberStatus": null
            },
            {
                "id": 137619,
                "legislatorId": 183,
                "voteType": "NO",
                "votingMemberStatus": null
            },
            {
                "id": 137584,
                "legislatorId": 184,
                "voteType": "YES",
                "votingMemberStatus": null
            },
            {
                "id": 137650,
                "legislatorId": 185,
                "voteType": "EXCUSED",
                "votingMemberStatus": null
            },
            {
                "id": 137603,
                "legislatorId": 186,
                "voteType": "NO",
                "votingMemberStatus": null
            },
            {
                "id": 137576,
                "legislatorId": 197,
                "voteType": "YES",
                "votingMemberStatus": null
            },
            {
                "id": 137631,
                "legislatorId": 199,
                "voteType": "NO",
                "votingMemberStatus": null
            },
            {
                "id": 137620,
                "legislatorId": 200,
                "voteType": "NO",
                "votingMemberStatus": null
            },
            {
                "id": 137579,
                "legislatorId": 201,
                "voteType": "YES",
                "votingMemberStatus": null
            },
            {
                "id": 137624,
                "legislatorId": 202,
                "voteType": "NO",
                "votingMemberStatus": null
            },
            {
                "id": 137555,
                "legislatorId": 223,
                "voteType": "YES",
                "votingMemberStatus": null
            },
            {
                "id": 137602,
                "legislatorId": 225,
                "voteType": "NO",
                "votingMemberStatus": null
            },
            {
                "id": 137623,
                "legislatorId": 226,
                "voteType": "NO",
                "votingMemberStatus": null
            },
            {
                "id": 137600,
                "legislatorId": 227,
                "voteType": "NO",
                "votingMemberStatus": null
            },
            {
                "id": 137572,
                "legislatorId": 228,
                "voteType": "YES",
                "votingMemberStatus": null
            },
            {
                "id": 137609,
                "legislatorId": 230,
                "voteType": "NO",
                "votingMemberStatus": null
            },
            {
                "id": 137559,
                "legislatorId": 231,
                "voteType": "YES",
                "votingMemberStatus": null
            },
            {
                "id": 137649,
                "legislatorId": 232,
                "voteType": "NO",
                "votingMemberStatus": null
            },
            {
                "id": 137590,
                "legislatorId": 233,
                "voteType": "YES",
                "votingMemberStatus": null
            },
            {
                "id": 137561,
                "legislatorId": 234,
                "voteType": "YES",
                "votingMemberStatus": null
            },
            {
                "id": 137560,
                "legislatorId": 236,
                "voteType": "YES",
                "votingMemberStatus": null
            },
            {
                "id": 137562,
                "legislatorId": 237,
                "voteType": "YES",
                "votingMemberStatus": null
            },
            {
                "id": 137587,
                "legislatorId": 240,
                "voteType": "YES",
                "votingMemberStatus": null
            },
            {
                "id": 137598,
                "legislatorId": 241,
                "voteType": "NO",
                "votingMemberStatus": null
            },
            {
                "id": 137638,
                "legislatorId": 272,
                "voteType": "NO",
                "votingMemberStatus": null
            },
            {
                "id": 137557,
                "legislatorId": 293,
                "voteType": "YES",
                "votingMemberStatus": null
            },
            {
                "id": 137567,
                "legislatorId": 304,
                "voteType": "YES",
                "votingMemberStatus": null
            }
        ],
        "billStatus": {
            "id": 52549,
            "timeStamp": "2025-03-05T20:26:00",
            "standingCommitteeId": null
        },
        "systemId": {
            "chamber": "HOUSE",
            "sequence": 1102
        }
    }
]